tl/__init__.py
tl/exp.py
tl/experiments/exp1.py
tl/experiments/exp10.py
tl/experiments/exp2.py
tl/experiments/exp3.py
tl/experiments/exp4.py
tl/experiments/exp5.py
tl/experiments/exp6.py
tl/experiments/exp7.py
tl/experiments/exp8.py
tl/experiments/exp9.py
aids_tl-0.0.0.dist-info/METADATA
aids_tl-0.0.0.dist-info/WHEEL
aids_tl-0.0.0.dist-info/top_level.txt
aids_tl-0.0.0.dist-info/RECORD
