Metadata-Version: 2.1
Name: aids-tl
Version: 0.0.0
Summary: A package to run 10 experiments via tl.exp(n)
Home-page: https://example.com
Author: TVKVIJAYCM
Author-email: tvkvijay0333@gmail.com
Classifier: Programming Language :: Python :: 3
Classifier: License :: OSI Approved :: MIT License
Classifier: Operating System :: OS Independent
